azure_llm_toolkit/__init__.py
azure_llm_toolkit/analytics.py
azure_llm_toolkit/batch.py
azure_llm_toolkit/batch_api.py
azure_llm_toolkit/batch_embedder.py
azure_llm_toolkit/cache.py
azure_llm_toolkit/circuit_breaker.py
azure_llm_toolkit/client.py
azure_llm_toolkit/client.py.bak
azure_llm_toolkit/config.py
azure_llm_toolkit/conversation.py
azure_llm_toolkit/cost_tracker.py
azure_llm_toolkit/dashboard.py
azure_llm_toolkit/health.py
azure_llm_toolkit/metrics.py
azure_llm_toolkit/opentelemetry_integration.py
azure_llm_toolkit/py.typed
azure_llm_toolkit/rate_limiter.py
azure_llm_toolkit/reranker.py
azure_llm_toolkit/streaming.py
azure_llm_toolkit/sync_client.py
azure_llm_toolkit/tools.py
azure_llm_toolkit/types.py
azure_llm_toolkit/validation.py
azure_llm_toolkit-0.2.1.dist-info/METADATA
azure_llm_toolkit-0.2.1.dist-info/WHEEL
azure_llm_toolkit-0.2.1.dist-info/licenses/LICENSE
azure_llm_toolkit-0.2.1.dist-info/RECORD
