Metadata-Version: 2.4
Name: azure-llm-toolkit
Version: 0.2.1
Summary: Azure OpenAI client wrapper with rate limiting, cost tracking, and retry logic
Project-URL: Homepage, https://github.com/torsteinsornes/azure-llm-toolkit
Project-URL: Repository, https://github.com/torsteinsornes/azure-llm-toolkit
Project-URL: Issues, https://github.com/torsteinsornes/azure-llm-toolkit/issues
Author-email: Torstein Sørnes <t.soernes@gmail.com>
License: MIT
License-File: LICENSE
Keywords: azure,chat,cost-tracking,embeddings,llm,openai,rate-limiting
Classifier: Development Status :: 4 - Beta
Classifier: Intended Audience :: Developers
Classifier: License :: OSI Approved :: MIT License
Classifier: Programming Language :: Python :: 3
Classifier: Programming Language :: Python :: 3.10
Classifier: Programming Language :: Python :: 3.11
Classifier: Programming Language :: Python :: 3.12
Classifier: Programming Language :: Python :: 3.13
Classifier: Topic :: Scientific/Engineering :: Artificial Intelligence
Classifier: Topic :: Software Development :: Libraries :: Python Modules
Requires-Python: >=3.10
Requires-Dist: numpy>=1.24.0
Requires-Dist: openai>=1.0.0
Requires-Dist: opentelemetry-api>=1.25.0
Requires-Dist: opentelemetry-exporter-otlp-proto-grpc>=1.25.0
Requires-Dist: opentelemetry-sdk>=1.25.0
Requires-Dist: polars>=0.19.0
Requires-Dist: prometheus-client>=0.20.0
Requires-Dist: pydantic>=2.0.0
Requires-Dist: python-dotenv>=1.0.0
Requires-Dist: tenacity>=8.0.0
Requires-Dist: tiktoken>=0.5.0
Requires-Dist: tqdm>=4.65.0
Provides-Extra: dev
Requires-Dist: basedpyright>=1.31.4; extra == 'dev'
Requires-Dist: mypy>=1.8.0; extra == 'dev'
Requires-Dist: pytest-asyncio>=0.23.0; extra == 'dev'
Requires-Dist: pytest>=8.0.0; extra == 'dev'
Requires-Dist: ruff>=0.6.0; extra == 'dev'
